ibdpainting/__init__.py
ibdpainting/command_line.py
ibdpainting/find_matching_markers.py
ibdpainting/ibd_scores.py
ibdpainting/ibd_table.py
ibdpainting/plot_ibd_table.py
ibdpainting-0.7.3.dist-info/METADATA
ibdpainting-0.7.3.dist-info/WHEEL
ibdpainting-0.7.3.dist-info/entry_points.txt
ibdpainting-0.7.3.dist-info/top_level.txt
ibdpainting-0.7.3.dist-info/RECORD
