Metadata-Version: 2.4
Name: ibdpainting
Version: 0.7.3
Summary: Identify parents of a crossed individual by comparing identity in windows across their genomes
Author-email: Tom Ellis <thomas.ellis@gmi.oeaw.ac.at>
Project-URL: Homepage, https://github.com/ellisztamas/ibdpainting
Requires-Python: >=3.7
Requires-Dist: numpy
Requires-Dist: pandas
Requires-Dist: plotly
Requires-Dist: h5py
Requires-Dist: scikit-allel
Requires-Dist: kaleido<1
Requires-Dist: tqdm
